zoom_deep_clean/__init__.py
zoom_deep_clean/advanced_detection.py
zoom_deep_clean/advanced_features.py
zoom_deep_clean/auth_fix_cli.py
zoom_deep_clean/auth_token_cleaner.py
zoom_deep_clean/cleaner_enhanced.py
zoom_deep_clean/cli_enhanced.py
zoom_deep_clean/comprehensive_cli.py
zoom_deep_clean/cross_platform_support.py
zoom_deep_clean/deep_system_cleaner.py
zoom_deep_clean/device_fingerprint_verifier.py
zoom_deep_clean/error_1132_handler.py
zoom_deep_clean/gui_app.py
zoom_deep_clean/gui_pyside6.py
zoom_deep_clean/gui_simple.py
zoom_deep_clean/macos_compatibility.py
zoom_deep_clean/performance_monitoring.py
zoom_deep_clean/performance_optimizations.py
zoom_deep_clean/security_enhancements.py
zoom_deep_clean/zoom_installer.py
zoom_deep_clean/zoom_installer_builtin.py
zoom_deep_clean_enhanced-2.4.2.dist-info/METADATA
zoom_deep_clean_enhanced-2.4.2.dist-info/WHEEL
zoom_deep_clean_enhanced-2.4.2.dist-info/entry_points.txt
zoom_deep_clean_enhanced-2.4.2.dist-info/top_level.txt
zoom_deep_clean_enhanced-2.4.2.dist-info/RECORD
