Metadata-Version: 2.4
Name: zoom-deep-clean-enhanced
Version: 2.4.2
Summary: Enhanced VM-Aware & System-Wide Zoom cleanup utility for macOS
Home-page: https://github.com/PHLthy215/zoom-deep-clean-enhanced
Author: PHLthy215
Author-email: PHLthy215@example.com
Project-URL: Bug Reports, https://github.com/PHLthy215/zoom-deep-clean-enhanced/issues
Project-URL: Source, https://github.com/PHLthy215/zoom-deep-clean-enhanced
Project-URL: Documentation, https://github.com/PHLthy215/zoom-deep-clean-enhanced/blob/main/README.md
Keywords: zoom,cleanup,privacy,macos,vm,virtual-machine,system-administration,security,fingerprint-removal,pypi-ready
Classifier: Development Status :: 5 - Production/Stable
Classifier: Intended Audience :: End Users/Desktop
Classifier: Intended Audience :: System Administrators
Classifier: License :: OSI Approved :: MIT License
Classifier: Operating System :: MacOS
Classifier: Programming Language :: Python :: 3
Classifier: Programming Language :: Python :: 3.7
Classifier: Programming Language :: Python :: 3.8
Classifier: Programming Language :: Python :: 3.9
Classifier: Programming Language :: Python :: 3.10
Classifier: Programming Language :: Python :: 3.11
Classifier: Topic :: System :: Systems Administration
Classifier: Topic :: Utilities
Classifier: Environment :: Console
Requires-Python: >=3.7
Provides-Extra: dev
Requires-Dist: pytest>=6.0; extra == "dev"
Requires-Dist: pytest-cov>=2.0; extra == "dev"
Requires-Dist: black>=21.0; extra == "dev"
Requires-Dist: flake8>=3.8; extra == "dev"
Requires-Dist: mypy>=0.800; extra == "dev"
Dynamic: author
Dynamic: author-email
Dynamic: classifier
Dynamic: description
Dynamic: description-content-type
Dynamic: home-page
Dynamic: keywords
Dynamic: project-url
Dynamic: provides-extra
Dynamic: requires-python
Dynamic: summary
